znum/__init__.py
znum/core.py
znum/dist.py
znum/exceptions.py
znum/math_ops.py
znum/promethee.py
znum/sort.py
znum/topsis.py
znum/utils.py
znum/valid.py
znum/vikor.py
znum/ztype.py
znum-0.5.0.dist-info/METADATA
znum-0.5.0.dist-info/WHEEL
znum-0.5.0.dist-info/RECORD
