Metadata-Version: 2.4
Name: znum
Version: 0.5.0
Summary: Z-number data type for fuzzy arithmetic and multi-criteria decision making (TOPSIS, VIKOR, PROMETHEE)
Project-URL: Homepage, https://github.com/maganuriyev/znum
Project-URL: Repository, https://github.com/maganuriyev/znum
Project-URL: Issues, https://github.com/maganuriyev/znum/issues
Author-email: Maga Nuriyev <maganuriyev@gmail.com>
License-Expression: MIT
Keywords: fuzzy-arithmetic,fuzzy-number,mcdm,multi-criteria-decision-making,optimization,promethee,topsis,vikor,z-number
Classifier: Development Status :: 4 - Beta
Classifier: Intended Audience :: Developers
Classifier: Intended Audience :: Science/Research
Classifier: License :: OSI Approved :: MIT License
Classifier: Operating System :: OS Independent
Classifier: Programming Language :: Python :: 3
Classifier: Programming Language :: Python :: 3.10
Classifier: Programming Language :: Python :: 3.11
Classifier: Programming Language :: Python :: 3.12
Classifier: Programming Language :: Python :: 3.13
Classifier: Topic :: Scientific/Engineering :: Artificial Intelligence
Classifier: Topic :: Scientific/Engineering :: Mathematics
Requires-Python: >=3.10
Requires-Dist: numpy>=1.24.0
Requires-Dist: scipy>=1.10.0
Provides-Extra: dev
Requires-Dist: pytest>=7.0.0; extra == 'dev'
